[
  {
    "id": "P-38",
    "naziv": "Parcela 38",
    "koordinate": [
      [44.808058, 20.488684],
      [44.807824, 20.489014],
       [44.807424, 20.488456],
      [44.807689, 20.488102],     
      [44.808058, 20.488684]   
    ]
  },
  {
    "id": "P-52",
    "naziv": "Parcela 52",
    "koordinate": [
      [44.8075, 20.4889],
      [44.8075, 20.4893],
      [44.8072, 20.4893],
      [44.8072, 20.4889],
      [44.8075, 20.4889]
    ]
  },
  {
    "id": "P-82C",
    "naziv": "Parcela 82C",
    "koordinate": [
      [44.8070, 20.4897],
      [44.8070, 20.4901],
      [44.8067, 20.4901],
      [44.8067, 20.4897],
      [44.8070, 20.4897]
    ]
  }
]
